ebs/__init__.py
ebs/iot/__init__.py
ebs/iot/linuxnode/__init__.py
ebs/iot/linuxnode/background.py
ebs/iot/linuxnode/basemixin.py
ebs/iot/linuxnode/basenode.py
ebs/iot/linuxnode/browser.py
ebs/iot/linuxnode/busy.py
ebs/iot/linuxnode/common.py
ebs/iot/linuxnode/config.py
ebs/iot/linuxnode/constants.py
ebs/iot/linuxnode/events.py
ebs/iot/linuxnode/externalplayer.py
ebs/iot/linuxnode/gallery.py
ebs/iot/linuxnode/http.py
ebs/iot/linuxnode/log.py
ebs/iot/linuxnode/marquee.py
ebs/iot/linuxnode/mediaplayer.py
ebs/iot/linuxnode/nodeid.py
ebs/iot/linuxnode/resources.py
ebs/iot/linuxnode/structure.py
ebs/iot/linuxnode/text.py
ebs/iot/linuxnode/animations/__init__.py
ebs/iot/linuxnode/animations/composite.py
ebs/iot/linuxnode/images/no-internet.png
ebs/iot/linuxnode/images/no-server.png
ebs/iot/linuxnode/modapi/__init__.py
ebs/iot/linuxnode/modapi/engine.py
ebs/iot/linuxnode/modapi/manager.py
ebs/iot/linuxnode/modapi/primitives.py
ebs/iot/linuxnode/modapi/standalone.py
ebs/iot/linuxnode/profiling/__init__.py
ebs/iot/linuxnode/profiling/memory.py
ebs/iot/linuxnode/shell/__init__.py
ebs/iot/linuxnode/shell/network.py
ebs/iot/linuxnode/tables/__init__.py
ebs/iot/linuxnode/tables/animated.py
ebs/iot/linuxnode/tables/basic.py
ebs/iot/linuxnode/tables/renderable.py
ebs/iot/linuxnode/tables/spec.py
ebs/iot/linuxnode/tables/translatable.py
ebs/iot/linuxnode/timetable/__init__.py
ebs/iot/linuxnode/timetable/base.py
ebs/iot/linuxnode/widgets/__init__.py
ebs/iot/linuxnode/widgets/buttons.py
ebs/iot/linuxnode/widgets/clocks.py
ebs/iot/linuxnode/widgets/colors.py
ebs/iot/linuxnode/widgets/gallery.py
ebs/iot/linuxnode/widgets/image.py
ebs/iot/linuxnode/widgets/labels.py
ebs/iot/linuxnode/widgets/marquee.py
ebs/iot/linuxnode/widgets/pdfplayer.py
ebs_iot_linuxnode-1.7.5.dist-info/METADATA
ebs_iot_linuxnode-1.7.5.dist-info/WHEEL
ebs_iot_linuxnode-1.7.5.dist-info/top_level.txt
ebs_iot_linuxnode-1.7.5.dist-info/RECORD
