Metadata-Version: 2.1
Name: ebs-iot-linuxnode
Version: 1.7.5
Summary: UNKNOWN
Home-page: UNKNOWN
Author: Chintalagiri Shashank
Author-email: shashank.chintalagiri@gmail.com
License: UNKNOWN
Platform: UNKNOWN
Classifier: Development Status :: 5 - Production/Stable
Classifier: Intended Audience :: Developers
Classifier: License :: OSI Approved :: GNU General Public License v3 or later (GPLv3+)
Classifier: Programming Language :: Python
Classifier: Programming Language :: Python :: 3
Classifier: Programming Language :: Python :: 3.6
Classifier: Operating System :: POSIX :: Linux
Requires-Dist: six
Requires-Dist: setuptools-scm
Requires-Dist: appdirs
Requires-Dist: Cython
Requires-Dist: twisted[tls]
Requires-Dist: SQLAlchemy
Requires-Dist: kivy (>=1.11.1)
Requires-Dist: kivy-garden
Requires-Dist: arrow
Requires-Dist: raspi-system
Requires-Dist: netifaces
Requires-Dist: ifcfg
Requires-Dist: colorthief
Requires-Dist: treq
Requires-Dist: cached-property
Requires-Dist: pqueue
Requires-Dist: selenium
Requires-Dist: omxplayer-wrapper
Requires-Dist: pymediainfo
Requires-Dist: pdf2image
Requires-Dist: hoshi
